solid_backend/__init__.py
solid_backend/contact/__init__.py
solid_backend/contact/apps.py
solid_backend/contact/migrations/__init__.py
solid_backend/contact/serializers.py
solid_backend/contact/tests/__init__.py
solid_backend/contact/tests/conftest.py
solid_backend/contact/tests/conftest_files/__init__.py
solid_backend/contact/tests/conftest_files/general_conftest.py
solid_backend/contact/tests/test_serializers.py
solid_backend/contact/urls.py
solid_backend/contact/views.py
solid_backend/content/__init__.py
solid_backend/content/admin.py
solid_backend/content/apps.py
solid_backend/content/fields.py
solid_backend/content/migrations/0001_create_tree_node_model.py
solid_backend/content/migrations/0002_remove_treenode_is_top_level.py
solid_backend/content/migrations/0003_rename_treenode_node_name.py
solid_backend/content/migrations/0004_rename_treenode_info_text.py
solid_backend/content/migrations/0005_alter_treenode_name_attributes.py
solid_backend/content/migrations/__init__.py
solid_backend/content/models.py
solid_backend/content/serializers.py
solid_backend/content/tests/__init__.py
solid_backend/content/tests/conftest.py
solid_backend/content/tests/conftest_files/__init__.py
solid_backend/content/tests/conftest_files/general_conftest.py
solid_backend/content/tests/test_base_models.py
solid_backend/content/urls.py
solid_backend/content/views.py
solid_backend/glossary/__init__.py
solid_backend/glossary/admin.py
solid_backend/glossary/apps.py
solid_backend/glossary/forms.py
solid_backend/glossary/migrations/0001_implement_glossary_entry_model.py
solid_backend/glossary/migrations/0002_update_image_upload_path.py
solid_backend/glossary/migrations/0003_add_verbose_name_to_text_field.py
solid_backend/glossary/migrations/0004_remove_img_fields.py
solid_backend/glossary/migrations/0005_fields_optional.py
solid_backend/glossary/migrations/0006_auto_20220217_1858.py
solid_backend/glossary/migrations/0007_glossaryentry_tags.py
solid_backend/glossary/migrations/__init__.py
solid_backend-0.3.9.dist-info/LICENSE
solid_backend-0.3.9.dist-info/WHEEL
solid_backend-0.3.9.dist-info/METADATA
solid_backend-0.3.9.dist-info/RECORD
